LICENSE
MANIFEST.in
README.md
setup.py
taskee/__init__.py
taskee/dispatcher.py
taskee/events.py
taskee/states.py
taskee/taskee.py
taskee/tasks.py
taskee/utils.py
taskee.egg-info/PKG-INFO
taskee.egg-info/SOURCES.txt
taskee.egg-info/dependency_links.txt
taskee.egg-info/entry_points.txt
taskee.egg-info/requires.txt
taskee.egg-info/top_level.txt
taskee/cli/__init__.py
taskee/cli/cli.py
taskee/cli/styles.py
taskee/cli/commands/__init__.py
taskee/cli/commands/dashboard.py
taskee/cli/commands/log.py
taskee/cli/commands/tasks.py
taskee/cli/commands/test.py
taskee/notifiers/__init__.py
taskee/notifiers/native.py
taskee/notifiers/notifier.py
taskee/notifiers/pushbullet.py
taskee/notifiers/icons/taskee.png
tests/__init__.py
tests/ee_tasks.py
tests/mock_notification.py
tests/mock_notifier.py
tests/mock_taskee.py
tests/mock_tasks.py
tests/test_tasks.py
tests/test_utils.py