Metadata-Version: 2.1
Name: taskee
Version: 0.0.4
Summary: Notifications for Earth Engine tasks.
Home-page: https://github.com/aazuspan/taskee
Author: Aaron Zuspan
Author-email: aa.zuspan@gmail.com
License: GPLv3+
Keywords: earth-engine,notifications,tasks,cli,command-line
Platform: UNKNOWN
Requires-Python: >=3.7
Provides-Extra: dev
Provides-Extra: test
License-File: LICENSE
